veikk/__init__.py
veikk/evdev_manager.py
veikk/udev_manager.py
veikk/veikk_config_manager.py
veikk/veikk_daemon.py
veikk/veikk_device.py
veikkctl/__init__.py
veikk_config-3.0.0a1.dist-info/LICENSE
veikk_config-3.0.0a1.dist-info/METADATA
veikk_config-3.0.0a1.dist-info/WHEEL
veikk_config-3.0.0a1.dist-info/entry_points.txt
veikk_config-3.0.0a1.dist-info/top_level.txt
veikk_config-3.0.0a1.dist-info/RECORD
