Metadata-Version: 2.1
Name: veikk-config
Version: 3.0.0a1
Summary: VEIKK Digitizer Configuration Tool
Home-page: https://www.github.com/jlam55555/veikk-config
Author: Jonathan Lam
Author-email: jlam55555@gmail.com
License: GNU General Public License v2.0
Platform: UNKNOWN
License-File: LICENSE
Requires-Dist: pyudev
Requires-Dist: evdev
